puan_client_db/__init__.py
puan_client_db-0.0.4.dist-info/LICENSE
puan_client_db-0.0.4.dist-info/METADATA
puan_client_db-0.0.4.dist-info/WHEEL
puan_client_db-0.0.4.dist-info/top_level.txt
puan_client_db-0.0.4.dist-info/RECORD
