Metadata-Version: 2.1
Name: puan-client-db
Version: 0.0.4
Summary: SDK for calling running http service of puan-server-db
Author-email: Our Studio Void AB <moa@ourstudio.se>
Keywords: combinatorial optimization,database,service,propositional logic,optimization
Classifier: Programming Language :: Python :: 3
Classifier: Operating System :: OS Independent
Requires-Python: >=3.9
License-File: LICENSE
Requires-Dist: puan (>=0.5.0)
Requires-Dist: requests (>=2.28.2)
